{
  "tenderid": 0,
  "tenderrefno": null,
  "publisheDateFrom": null,
  "publishDateTo": null,
  "closeDateFrom": null,
  "closeDateTo": null,
  "valueCriteriaFrom": null,
  "valueCriteriaTo": null,
  "bidPartList": null,
  "procurementCategoryList": null,
  "stateList": null,
  "tenderTypeList": null,
  "tenderCategoryList": null,
  "corrigendumFlag": null,
  "orgId": 0,
  "deptId": 0,
  "valueCriteriaId": 0,
  "dateCriteriaId": 0,
  "valueTypeId": 0,
  "dateCriteriaFrom": null,
  "dateCriteriaTo": null,
  "itemTitle": null,
  "isRollBack": "N",
  "currenttenderid": 58908,
  "currentOrgTenderId": 58762,
  "currenttenderrefno": "03/2023-24/FCDKHG2/G01",
  "currentgroupid": 0,
  "currentorgid": 538,
  "currentdeptid": 731,
  "currenttendertypeid": 101,
  "currenttendercatid": 101,
  "currentproccatid": 1557,
  "currentpacamt": null,
  "currentstatus": 7,
  "currentauctionflag": null,
  "currentauctiontype": null,
  "currentinitiateauction": null,
  "currentdescription": "Anti Erosion work in Madhura village in front of Km 35.240 of K.B. embankment (Agenda No-211/258/2024)",
  "currentownerdegitalcertid": null,
  "currenttendercurrency": null,
  "currentbidcurrency": null,
  "currentminbidno": 0,
  "currenttendercallno": 0,
  "currentqueryString": null,
  "currentindentNo": null,
  "currentBidPartNo": 2,
  "currentbidEndDate": 1710149400000,
  "currentbidStartDate": 1709719200000,
  "currentbidOpenDate": 1710324000000,
  "currentDocSubmissionEndDate": null,
  "currentTenderPublishDate": 1709717706000,
  "currentTenderCancelDate": null,
  "currentTenderCancelReason": null,
  "currentTenderCancelAttachment": null,
  "currentTenderCancelAttachmentPath": null,
  "startDate": null,
  "endDate": null,
  "dateParam": 0,
  "procatId": 0,
  "typeId": 0,
  "textFilter": null
}