{
  "tenderid": 0,
  "tenderrefno": null,
  "publisheDateFrom": null,
  "publishDateTo": null,
  "closeDateFrom": null,
  "closeDateTo": null,
  "valueCriteriaFrom": null,
  "valueCriteriaTo": null,
  "bidPartList": null,
  "procurementCategoryList": null,
  "stateList": null,
  "tenderTypeList": null,
  "tenderCategoryList": null,
  "corrigendumFlag": null,
  "orgId": 0,
  "deptId": 0,
  "valueCriteriaId": 0,
  "dateCriteriaId": 0,
  "valueTypeId": 0,
  "dateCriteriaFrom": null,
  "dateCriteriaTo": null,
  "itemTitle": null,
  "isRollBack": "N",
  "currenttenderid": 61117,
  "currentOrgTenderId": 60971,
  "currenttenderrefno": "NIT-01/2023-24/GROUP-02/IMD DARBHANGA",
  "currentgroupid": 0,
  "currentorgid": 538,
  "currentdeptid": 731,
  "currenttendertypeid": 101,
  "currenttendercatid": 101,
  "currentproccatid": 1556,
  "currentpacamt": null,
  "currentstatus": 6,
  "currentauctionflag": null,
  "currentauctiontype": null,
  "currentinitiateauction": null,
  "currentdescription": "General maintenance & repair of A.F.S Gate & its components situated  at    K.M- 24.00, 26.90, 28.50, 34.70, 35.90, 53.00, 63.30, 65.20, 68.00, 71.20, 72.20, 75.00, 80.90 of K.B.L.E, at K.M- 1.30, 6.00, 22.50, 26.45, 28.97 of B.B.R.E., at K.M- 11.20, 25.488, 28.470, 29.710 of B.B.L.E, at K.M- 0.40, 1.10, 1.60, 3.10, 3.50, 4.50, 5.10 of chandpura  ring bundh and at K.M- 1.59 & 5.20 of Agropatti Basaitha ring bundh, at K.M- 7.20, 8.40, 13.50 and at Mithila hat under F.C Division- 01  Jhanjharpur.",
  "currentownerdegitalcertid": null,
  "currenttendercurrency": null,
  "currentbidcurrency": null,
  "currentminbidno": 0,
  "currenttendercallno": 0,
  "currentqueryString": null,
  "currentindentNo": null,
  "currentBidPartNo": 2,
  "currentbidEndDate": 1714555823000,
  "currentbidStartDate": 1714098623000,
  "currentbidOpenDate": 1714644023000,
  "currentDocSubmissionEndDate": null,
  "currentTenderPublishDate": 1714081044000,
  "currentTenderCancelDate": null,
  "currentTenderCancelReason": null,
  "currentTenderCancelAttachment": null,
  "currentTenderCancelAttachmentPath": null,
  "startDate": null,
  "endDate": null,
  "dateParam": 0,
  "procatId": 0,
  "typeId": 0,
  "textFilter": null
}