{
  "tenderid": 0,
  "tenderrefno": null,
  "publisheDateFrom": null,
  "publishDateTo": null,
  "closeDateFrom": null,
  "closeDateTo": null,
  "valueCriteriaFrom": null,
  "valueCriteriaTo": null,
  "bidPartList": null,
  "procurementCategoryList": null,
  "stateList": null,
  "tenderTypeList": null,
  "tenderCategoryList": null,
  "corrigendumFlag": null,
  "orgId": 0,
  "deptId": 0,
  "valueCriteriaId": 0,
  "dateCriteriaId": 0,
  "valueTypeId": 0,
  "dateCriteriaFrom": null,
  "dateCriteriaTo": null,
  "itemTitle": null,
  "isRollBack": "N",
  "currenttenderid": 21196,
  "currentOrgTenderId": 21098,
  "currenttenderrefno": "04/2021-22 GR17",
  "currentgroupid": 0,
  "currentorgid": 538,
  "currentdeptid": 800,
  "currenttendertypeid": 101,
  "currenttendercatid": 101,
  "currentproccatid": 1557,
  "currentpacamt": null,
  "currentstatus": 7,
  "currentauctionflag": null,
  "currentauctiontype": null,
  "currentinitiateauction": null,
  "currentdescription": "NAGAR PARISHAD WARD 01 ME MUKHYA SADAK SE HIRALAL SINGH KE DALAN TAK ROAD KE DONO TARAF PAVER BLOCK AVM NALI NIRMAN KARYA",
  "currentownerdegitalcertid": null,
  "currenttendercurrency": null,
  "currentbidcurrency": null,
  "currentminbidno": 0,
  "currenttendercallno": 0,
  "currentqueryString": null,
  "currentindentNo": null,
  "currentBidPartNo": 1,
  "currentbidEndDate": 1651311036000,
  "currentbidStartDate": 1650879036000,
  "currentbidOpenDate": 1651829400000,
  "currentDocSubmissionEndDate": 1651743036000,
  "currentTenderPublishDate": 1650808612000,
  "currentTenderCancelDate": null,
  "currentTenderCancelReason": null,
  "currentTenderCancelAttachment": null,
  "currentTenderCancelAttachmentPath": null,
  "startDate": null,
  "endDate": null,
  "dateParam": 0,
  "procatId": 0,
  "typeId": 0,
  "textFilter": null
}