{
  "tenderid": 0,
  "tenderrefno": null,
  "publisheDateFrom": null,
  "publishDateTo": null,
  "closeDateFrom": null,
  "closeDateTo": null,
  "valueCriteriaFrom": null,
  "valueCriteriaTo": null,
  "bidPartList": null,
  "procurementCategoryList": null,
  "stateList": null,
  "tenderTypeList": null,
  "tenderCategoryList": null,
  "corrigendumFlag": null,
  "orgId": 0,
  "deptId": 0,
  "valueCriteriaId": 0,
  "dateCriteriaId": 0,
  "valueTypeId": 0,
  "dateCriteriaFrom": null,
  "dateCriteriaTo": null,
  "itemTitle": null,
  "isRollBack": "N",
  "currenttenderid": 26389,
  "currentOrgTenderId": 26243,
  "currenttenderrefno": "NIQ_04/BCD/MOTIHARI/2022-23",
  "currentgroupid": 0,
  "currentorgid": 538,
  "currentdeptid": 1026,
  "currenttendertypeid": 101,
  "currenttendercatid": 102,
  "currentproccatid": 1554,
  "currentpacamt": null,
  "currentstatus": 6,
  "currentauctionflag": null,
  "currentauctiontype": null,
  "currentinitiateauction": null,
  "currentdescription": "Comprehensive House Keeping, Maintenance and operation contract (for 5 years) of 2000 Capacity Prekshagrih, Motihari,",
  "currentownerdegitalcertid": null,
  "currenttendercurrency": null,
  "currentbidcurrency": null,
  "currentminbidno": 0,
  "currenttendercallno": 0,
  "currentqueryString": null,
  "currentindentNo": null,
  "currentBidPartNo": 2,
  "currentbidEndDate": 1665221400000,
  "currentbidStartDate": 1663588834000,
  "currentbidOpenDate": 1665396034000,
  "currentDocSubmissionEndDate": 1665394234000,
  "currentTenderPublishDate": 1663583358000,
  "currentTenderCancelDate": null,
  "currentTenderCancelReason": null,
  "currentTenderCancelAttachment": null,
  "currentTenderCancelAttachmentPath": null,
  "startDate": null,
  "endDate": null,
  "dateParam": 0,
  "procatId": 0,
  "typeId": 0,
  "textFilter": null
}