{
  "tenderid": 0,
  "tenderrefno": null,
  "publisheDateFrom": null,
  "publishDateTo": null,
  "closeDateFrom": null,
  "closeDateTo": null,
  "valueCriteriaFrom": null,
  "valueCriteriaTo": null,
  "bidPartList": null,
  "procurementCategoryList": null,
  "stateList": null,
  "tenderTypeList": null,
  "tenderCategoryList": null,
  "corrigendumFlag": null,
  "orgId": 0,
  "deptId": 0,
  "valueCriteriaId": 0,
  "dateCriteriaId": 0,
  "valueTypeId": 0,
  "dateCriteriaFrom": null,
  "dateCriteriaTo": null,
  "itemTitle": null,
  "isRollBack": "N",
  "currenttenderid": 29565,
  "currentOrgTenderId": 29419,
  "currenttenderrefno": "NIT NO. 04 /2022 - 23",
  "currentgroupid": 0,
  "currentorgid": 538,
  "currentdeptid": 731,
  "currenttendertypeid": 101,
  "currenttendercatid": 101,
  "currentproccatid": 1557,
  "currentpacamt": null,
  "currentstatus": 7,
  "currentauctionflag": null,
  "currentauctiontype": null,
  "currentinitiateauction": null,
  "currentdescription": "BILL OF QUANTITY FOR ANTI EROSION WORKS FOR PROTECTION OF RIVER EDGE IN U/S, D/S AND IN BETWEEN SPUR CH. 42 AND SPUR 67 AT GOVINDPUR BHOLAMARI OF LABHA CHAUKIA PAHARPUR MAHANANDA RIGHT EMBANKMENT   (Agenda no:-194/105/2023) UNDER FLOOD CONTROL DIVISION, KATIHAR",
  "currentownerdegitalcertid": null,
  "currenttendercurrency": null,
  "currentbidcurrency": null,
  "currentminbidno": 0,
  "currenttendercallno": 0,
  "currentqueryString": null,
  "currentindentNo": null,
  "currentBidPartNo": 2,
  "currentbidEndDate": 1672221600000,
  "currentbidStartDate": 1671885000000,
  "currentbidOpenDate": 1672394400000,
  "currentDocSubmissionEndDate": 1672392600000,
  "currentTenderPublishDate": 1671882258000,
  "currentTenderCancelDate": null,
  "currentTenderCancelReason": null,
  "currentTenderCancelAttachment": null,
  "currentTenderCancelAttachmentPath": null,
  "startDate": null,
  "endDate": null,
  "dateParam": 0,
  "procatId": 0,
  "typeId": 0,
  "textFilter": null
}